odoo/addons/account_cutoff_accrual_dates/README.rst
odoo/addons/account_cutoff_accrual_dates/__init__.py
odoo/addons/account_cutoff_accrual_dates/__manifest__.py
odoo/addons/account_cutoff_accrual_dates/i18n/account_cutoff_accrual_dates.pot
odoo/addons/account_cutoff_accrual_dates/i18n/de.po
odoo/addons/account_cutoff_accrual_dates/i18n/es.po
odoo/addons/account_cutoff_accrual_dates/i18n/fr.po
odoo/addons/account_cutoff_accrual_dates/i18n/it.po
odoo/addons/account_cutoff_accrual_dates/i18n/pt.po
odoo/addons/account_cutoff_accrual_dates/i18n/pt_BR.po
odoo/addons/account_cutoff_accrual_dates/i18n/sl.po
odoo/addons/account_cutoff_accrual_dates/models/__init__.py
odoo/addons/account_cutoff_accrual_dates/models/account_cutoff.py
odoo/addons/account_cutoff_accrual_dates/readme/CONFIGURE.rst
odoo/addons/account_cutoff_accrual_dates/readme/CONTRIBUTORS.rst
odoo/addons/account_cutoff_accrual_dates/readme/DESCRIPTION.rst
odoo/addons/account_cutoff_accrual_dates/readme/USAGE.rst
odoo/addons/account_cutoff_accrual_dates/static/description/icon.png
odoo/addons/account_cutoff_accrual_dates/static/description/index.html
odoo12_addon_account_cutoff_accrual_dates-12.0.1.0.1.dist-info/METADATA
odoo12_addon_account_cutoff_accrual_dates-12.0.1.0.1.dist-info/WHEEL
odoo12_addon_account_cutoff_accrual_dates-12.0.1.0.1.dist-info/top_level.txt
odoo12_addon_account_cutoff_accrual_dates-12.0.1.0.1.dist-info/RECORD
