Metadata-Version: 2.1
Name: odoo12-addon-account-cutoff-accrual-dates
Version: 12.0.1.0.1
Summary: Accrued expenses and revenues based on start/end dates
Home-page: http://www.akretion.com
Author: Akretion,Odoo Community Association (OCA)
Author-email: support@odoo-community.org
License: AGPL-3
Platform: UNKNOWN
Classifier: Programming Language :: Python
Classifier: Framework :: Odoo
Classifier: License :: OSI Approved :: GNU Affero General Public License v3
Requires-Python: >=3.5
Requires-Dist: odoo12-addon-account-cutoff-accrual-base
Requires-Dist: odoo12-addon-account-cutoff-prepaid
Requires-Dist: odoo (<12.1dev,>=12.0a)
